fake_data_agents/__init__.py
fake_data_agents/faker.py
fake_data_agents/prompt.py
fake_data_agents/core/__init__.py
fake_data_agents/core/agents.py
fake_data_agents/core/providers.py
fake_data_agents/recipe/__init__.py
fake_data_agents/recipe/base.py
fake_data_agents/recipe/llm.py
fake_data_agents-0.5.3.dist-info/METADATA
fake_data_agents-0.5.3.dist-info/WHEEL
fake_data_agents-0.5.3.dist-info/top_level.txt
fake_data_agents-0.5.3.dist-info/RECORD
