Metadata-Version: 2.1
Name: fake-data-agents
Version: 0.5.3
Summary: Python library for generating synthetic data with LLMs
Project-URL: Homepage, https://github.com/hamilak/fake-data-agents
Project-URL: Issues, https://github.com/hamilak/fake-data-agents/issues
Requires-Python: >=3.12
Requires-Dist: google-generativeai >=0.8.3
Requires-Dist: openai >=1.52.0
Requires-Dist: protobuf >=5.28.2
Requires-Dist: pytest >=8.3.3
Requires-Dist: python-dotenv >=1.0.1
Requires-Dist: requests >=2.32.3
